majoplot/__init__.py
majoplot/__main__.py
majoplot/config.json
majoplot/app/__init__.py
majoplot/app/cli.py
majoplot/app/gui.py
majoplot/domain/base.py
majoplot/domain/muti_axes_spec.py
majoplot/domain/utils.py
majoplot/domain/importers/PPMS_Resistivity.py
majoplot/domain/importers/VSM.py
majoplot/domain/importers/XRD.py
majoplot/domain/scenarios/PPMS_Resistivity/RT.py
majoplot/domain/scenarios/VSM/ChiT.py
majoplot/domain/scenarios/VSM/ChiT_onlyZFC.py
majoplot/domain/scenarios/VSM/MT.py
majoplot/domain/scenarios/VSM/MT_insert.py
majoplot/domain/scenarios/VSM/MT_origin.py
majoplot/domain/scenarios/VSM/MT_reliability_analysis.py
majoplot/domain/scenarios/XRD/Compare.py
majoplot/gui/__init__.py
majoplot/gui/main.py
majoplot/infra/plotters/matplot.py
majoplot/infra/plotters/origin.py
majoplot/infra/plotters/origin_utils/originlab_type_library.py
majoplot-0.1.8.dist-info/METADATA
majoplot-0.1.8.dist-info/WHEEL
majoplot-0.1.8.dist-info/entry_points.txt
majoplot-0.1.8.dist-info/licenses/LICENSE
majoplot-0.1.8.dist-info/RECORD
