Metadata-Version: 2.4
Name: majoplot
Version: 0.1.8
Summary: Automates scenario-specific data preprocessing and plotting workflows for condensed-matter physics labs (OriginLab COM backend + Matplotlib for preview).
Project-URL: Homepage, https://github.com/ponyofshadows/majoplot
Project-URL: Source, https://github.com/ponyofshadows/majoplot
Project-URL: Issues, https://github.com/ponyofshadows/majoplot/issues
Author: ponyofshadows
License: MIT
License-File: LICENSE
Keywords: com,condensed-matter,materials-science,origin,originlab,plotting,ppms,vsm,xrd
Classifier: Intended Audience :: Science/Research
Classifier: License :: OSI Approved :: MIT License
Classifier: Operating System :: Microsoft :: Windows
Classifier: Operating System :: OS Independent
Classifier: Programming Language :: Python :: 3
Classifier: Programming Language :: Python :: 3.11
Classifier: Programming Language :: Python :: 3.12
Classifier: Programming Language :: Python :: 3.13
Classifier: Topic :: Scientific/Engineering :: Physics
Classifier: Topic :: Scientific/Engineering :: Visualization
Requires-Python: >=3.11
Requires-Dist: matplotlib>=3.8
Requires-Dist: numpy>=2.0
Requires-Dist: pywin32>=311; platform_system == 'Windows'
